flake8_no_emoji/__init__.py
flake8_no_emoji/categories.py
flake8_no_emoji/checker.py
flake8_no_emoji-0.2.6.dist-info/licenses/LICENSE
flake8_no_emoji-0.2.6.dist-info/METADATA
flake8_no_emoji-0.2.6.dist-info/WHEEL
flake8_no_emoji-0.2.6.dist-info/entry_points.txt
flake8_no_emoji-0.2.6.dist-info/top_level.txt
flake8_no_emoji-0.2.6.dist-info/RECORD
