Metadata-Version: 2.4
Name: flake8-no-emoji
Version: 0.2.6
Summary: A Flake8 plugin that detects emojis in Python source code
Author: AlgorithmAlchemy
License: MIT
Keywords: flake8,plugin,emoji,linter,pre-commit,unicode,code style,static analysis,code quality,no-emoji-in-code
Classifier: Development Status :: 5 - Production/Stable
Classifier: Intended Audience :: Developers
Classifier: Topic :: Software Development :: Quality Assurance
Classifier: Topic :: Software Development :: Libraries :: Python Modules
Classifier: Topic :: Text Processing :: Linguistic
Classifier: Framework :: Flake8
Classifier: Programming Language :: Python :: 3
Classifier: Programming Language :: Python :: 3.8
Classifier: Programming Language :: Python :: 3.9
Classifier: Programming Language :: Python :: 3.10
Classifier: Programming Language :: Python :: 3.11
Classifier: Programming Language :: Python :: 3.12
Classifier: Programming Language :: Python :: 3.13
Classifier: License :: OSI Approved :: MIT License
Requires-Python: >=3.8
License-File: LICENSE
Requires-Dist: regex
Requires-Dist: emoji>=2.0.0
Dynamic: license-file
